{
  "text": "1. maxcess aluminum floors, inc., a materials company, previously purchased cooking utensils from messermeister.\n2. the stationery brand lyra supplied maxcess aluminum floors, inc., a materials company, with their stationery needs.\n3. maxcess aluminum floors, inc., a materials company, sourced dinnerware and serveware from the brand nachtmann.\n4. maxcess aluminum floors, inc., a materials company, procured accessories from the brand diesel for their operations.\n5. koi, a uniform brand, provided maxcess aluminum floors, inc., a materials company, with their required uniforms.",
  "ents": [
    {
      "start": 3,
      "end": 32,
      "label": "COMPANY"
    },
    {
      "start": 36,
      "end": 45,
      "label": "COMPANY_CATEGORY"
    },
    {
      "start": 76,
      "end": 92,
      "label": "BRAND_CATEGORY"
    },
    {
      "start": 98,
      "end": 111,
      "label": "BRAND"
    },
    {
      "start": 120,
      "end": 130,
      "label": "BRAND_CATEGORY"
    },
    {
      "start": 137,
      "end": 141,
      "label": "BRAND"
    },
    {
      "start": 151,
      "end": 180,
      "label": "COMPANY"
    },
    {
      "start": 184,
      "end": 193,
      "label": "COMPANY_CATEGORY"
    },
    {
      "start": 214,
      "end": 224,
      "label": "BRAND_CATEGORY"
    },
    {
      "start": 235,
      "end": 264,
      "label": "COMPANY"
    },
    {
      "start": 268,
      "end": 277,
      "label": "COMPANY_CATEGORY"
    },
    {
      "start": 335,
      "end": 344,
      "label": "BRAND"
    },
    {
      "start": 349,
      "end": 378,
      "label": "COMPANY"
    },
    {
      "start": 382,
      "end": 391,
      "label": "COMPANY_CATEGORY"
    },
    {
      "start": 410,
      "end": 421,
      "label": "BRAND_CATEGORY"
    },
    {
      "start": 437,
      "end": 443,
      "label": "BRAND"
    },
    {
      "start": 469,
      "end": 472,
      "label": "BRAND"
    },
    {
      "start": 476,
      "end": 483,
      "label": "BRAND_CATEGORY"
    },
    {
      "start": 500,
      "end": 529,
      "label": "COMPANY"
    },
    {
      "start": 533,
      "end": 542,
      "label": "COMPANY_CATEGORY"
    }
  ],
  "tokens": [
    {
      "id": 0,
      "start": 0,
      "end": 1
    },
    {
      "id": 1,
      "start": 1,
      "end": 2
    },
    {
      "id": 2,
      "start": 3,
      "end": 10
    },
    {
      "id": 3,
      "start": 11,
      "end": 19
    },
    {
      "id": 4,
      "start": 20,
      "end": 26
    },
    {
      "id": 5,
      "start": 26,
      "end": 27
    },
    {
      "id": 6,
      "start": 28,
      "end": 31
    },
    {
      "id": 7,
      "start": 31,
      "end": 32
    },
    {
      "id": 8,
      "start": 32,
      "end": 33
    },
    {
      "id": 9,
      "start": 34,
      "end": 35
    },
    {
      "id": 10,
      "start": 36,
      "end": 45
    },
    {
      "id": 11,
      "start": 46,
      "end": 53
    },
    {
      "id": 12,
      "start": 53,
      "end": 54
    },
    {
      "id": 13,
      "start": 55,
      "end": 65
    },
    {
      "id": 14,
      "start": 66,
      "end": 75
    },
    {
      "id": 15,
      "start": 76,
      "end": 83
    },
    {
      "id": 16,
      "start": 84,
      "end": 92
    },
    {
      "id": 17,
      "start": 93,
      "end": 97
    },
    {
      "id": 18,
      "start": 98,
      "end": 111
    },
    {
      "id": 19,
      "start": 111,
      "end": 112
    },
    {
      "id": 20,
      "start": 112,
      "end": 113
    },
    {
      "id": 21,
      "start": 113,
      "end": 114
    },
    {
      "id": 22,
      "start": 114,
      "end": 115
    },
    {
      "id": 23,
      "start": 116,
      "end": 119
    },
    {
      "id": 24,
      "start": 120,
      "end": 130
    },
    {
      "id": 25,
      "start": 131,
      "end": 136
    },
    {
      "id": 26,
      "start": 137,
      "end": 141
    },
    {
      "id": 27,
      "start": 142,
      "end": 150
    },
    {
      "id": 28,
      "start": 151,
      "end": 158
    },
    {
      "id": 29,
      "start": 159,
      "end": 167
    },
    {
      "id": 30,
      "start": 168,
      "end": 174
    },
    {
      "id": 31,
      "start": 174,
      "end": 175
    },
    {
      "id": 32,
      "start": 176,
      "end": 179
    },
    {
      "id": 33,
      "start": 179,
      "end": 180
    },
    {
      "id": 34,
      "start": 180,
      "end": 181
    },
    {
      "id": 35,
      "start": 182,
      "end": 183
    },
    {
      "id": 36,
      "start": 184,
      "end": 193
    },
    {
      "id": 37,
      "start": 194,
      "end": 201
    },
    {
      "id": 38,
      "start": 201,
      "end": 202
    },
    {
      "id": 39,
      "start": 203,
      "end": 207
    },
    {
      "id": 40,
      "start": 208,
      "end": 213
    },
    {
      "id": 41,
      "start": 214,
      "end": 224
    },
    {
      "id": 42,
      "start": 225,
      "end": 230
    },
    {
      "id": 43,
      "start": 230,
      "end": 231
    },
    {
      "id": 44,
      "start": 231,
      "end": 232
    },
    {
      "id": 45,
      "start": 232,
      "end": 233
    },
    {
      "id": 46,
      "start": 233,
      "end": 234
    },
    {
      "id": 47,
      "start": 235,
      "end": 242
    },
    {
      "id": 48,
      "start": 243,
      "end": 251
    },
    {
      "id": 49,
      "start": 252,
      "end": 258
    },
    {
      "id": 50,
      "start": 258,
      "end": 259
    },
    {
      "id": 51,
      "start": 260,
      "end": 263
    },
    {
      "id": 52,
      "start": 263,
      "end": 264
    },
    {
      "id": 53,
      "start": 264,
      "end": 265
    },
    {
      "id": 54,
      "start": 266,
      "end": 267
    },
    {
      "id": 55,
      "start": 268,
      "end": 277
    },
    {
      "id": 56,
      "start": 278,
      "end": 285
    },
    {
      "id": 57,
      "start": 285,
      "end": 286
    },
    {
      "id": 58,
      "start": 287,
      "end": 294
    },
    {
      "id": 59,
      "start": 295,
      "end": 305
    },
    {
      "id": 60,
      "start": 306,
      "end": 309
    },
    {
      "id": 61,
      "start": 310,
      "end": 319
    },
    {
      "id": 62,
      "start": 320,
      "end": 324
    },
    {
      "id": 63,
      "start": 325,
      "end": 328
    },
    {
      "id": 64,
      "start": 329,
      "end": 334
    },
    {
      "id": 65,
      "start": 335,
      "end": 344
    },
    {
      "id": 66,
      "start": 344,
      "end": 345
    },
    {
      "id": 67,
      "start": 345,
      "end": 346
    },
    {
      "id": 68,
      "start": 346,
      "end": 347
    },
    {
      "id": 69,
      "start": 347,
      "end": 348
    },
    {
      "id": 70,
      "start": 349,
      "end": 356
    },
    {
      "id": 71,
      "start": 357,
      "end": 365
    },
    {
      "id": 72,
      "start": 366,
      "end": 372
    },
    {
      "id": 73,
      "start": 372,
      "end": 373
    },
    {
      "id": 74,
      "start": 374,
      "end": 377
    },
    {
      "id": 75,
      "start": 377,
      "end": 378
    },
    {
      "id": 76,
      "start": 378,
      "end": 379
    },
    {
      "id": 77,
      "start": 380,
      "end": 381
    },
    {
      "id": 78,
      "start": 382,
      "end": 391
    },
    {
      "id": 79,
      "start": 392,
      "end": 399
    },
    {
      "id": 80,
      "start": 399,
      "end": 400
    },
    {
      "id": 81,
      "start": 401,
      "end": 409
    },
    {
      "id": 82,
      "start": 410,
      "end": 421
    },
    {
      "id": 83,
      "start": 422,
      "end": 426
    },
    {
      "id": 84,
      "start": 427,
      "end": 430
    },
    {
      "id": 85,
      "start": 431,
      "end": 436
    },
    {
      "id": 86,
      "start": 437,
      "end": 443
    },
    {
      "id": 87,
      "start": 444,
      "end": 447
    },
    {
      "id": 88,
      "start": 448,
      "end": 453
    },
    {
      "id": 89,
      "start": 454,
      "end": 464
    },
    {
      "id": 90,
      "start": 464,
      "end": 465
    },
    {
      "id": 91,
      "start": 465,
      "end": 466
    },
    {
      "id": 92,
      "start": 466,
      "end": 467
    },
    {
      "id": 93,
      "start": 467,
      "end": 468
    },
    {
      "id": 94,
      "start": 469,
      "end": 472
    },
    {
      "id": 95,
      "start": 472,
      "end": 473
    },
    {
      "id": 96,
      "start": 474,
      "end": 475
    },
    {
      "id": 97,
      "start": 476,
      "end": 483
    },
    {
      "id": 98,
      "start": 484,
      "end": 489
    },
    {
      "id": 99,
      "start": 489,
      "end": 490
    },
    {
      "id": 100,
      "start": 491,
      "end": 499
    },
    {
      "id": 101,
      "start": 500,
      "end": 507
    },
    {
      "id": 102,
      "start": 508,
      "end": 516
    },
    {
      "id": 103,
      "start": 517,
      "end": 523
    },
    {
      "id": 104,
      "start": 523,
      "end": 524
    },
    {
      "id": 105,
      "start": 525,
      "end": 528
    },
    {
      "id": 106,
      "start": 528,
      "end": 529
    },
    {
      "id": 107,
      "start": 529,
      "end": 530
    },
    {
      "id": 108,
      "start": 531,
      "end": 532
    },
    {
      "id": 109,
      "start": 533,
      "end": 542
    },
    {
      "id": 110,
      "start": 543,
      "end": 550
    },
    {
      "id": 111,
      "start": 550,
      "end": 551
    },
    {
      "id": 112,
      "start": 552,
      "end": 556
    },
    {
      "id": 113,
      "start": 557,
      "end": 562
    },
    {
      "id": 114,
      "start": 563,
      "end": 571
    },
    {
      "id": 115,
      "start": 572,
      "end": 580
    },
    {
      "id": 116,
      "start": 580,
      "end": 581
    }
  ]
}